odoo10_addon_account_mass_reconcile_partner-10.0.1.0.0.99.dev6-py3.8-nspkg.pth
odoo/addons/account_mass_reconcile_partner/README.rst
odoo/addons/account_mass_reconcile_partner/__init__.py
odoo/addons/account_mass_reconcile_partner/__manifest__.py
odoo/addons/account_mass_reconcile_partner/i18n/account_mass_reconcile_partner.pot
odoo/addons/account_mass_reconcile_partner/models/__init__.py
odoo/addons/account_mass_reconcile_partner/models/advanced_reconciliation.py
odoo/addons/account_mass_reconcile_partner/models/mass_reconcile.py
odoo/addons/account_mass_reconcile_partner/readme/CONTRIBUTORS.rst
odoo/addons/account_mass_reconcile_partner/readme/DESCRIPTION.rst
odoo/addons/account_mass_reconcile_partner/static/description/icon.png
odoo/addons/account_mass_reconcile_partner/static/description/index.html
odoo/addons/account_mass_reconcile_partner/tests/__init__.py
odoo/addons/account_mass_reconcile_partner/tests/test_reconcile_partner.py
odoo/addons/account_mass_reconcile_partner/views/mass_reconcile.xml
odoo10_addon_account_mass_reconcile_partner-10.0.1.0.0.99.dev6.dist-info/METADATA
odoo10_addon_account_mass_reconcile_partner-10.0.1.0.0.99.dev6.dist-info/WHEEL
odoo10_addon_account_mass_reconcile_partner-10.0.1.0.0.99.dev6.dist-info/namespace_packages.txt
odoo10_addon_account_mass_reconcile_partner-10.0.1.0.0.99.dev6.dist-info/top_level.txt
odoo10_addon_account_mass_reconcile_partner-10.0.1.0.0.99.dev6.dist-info/RECORD
