Metadata-Version: 2.1
Name: odoo10-addon-account-mass-reconcile-partner
Version: 10.0.1.0.0.99.dev6
Summary: Mass Reconcile Partner
Home-page: https://github.com/OCA/account-reconcile
Author: Camptocamp, Odoo Community Association (OCA)
Author-email: support@odoo-community.org
License: AGPL-3
Platform: UNKNOWN
Classifier: Programming Language :: Python
Classifier: Framework :: Odoo
Classifier: Framework :: Odoo :: 10.0
Classifier: License :: OSI Approved :: GNU Affero General Public License v3
Requires-Python: ~=2.7
Requires-Dist: odoo10-addon-account-mass-reconcile
Requires-Dist: odoo <10.1dev,>=10.0
